mambio/__init__.py
mambio-0.1.2.dist-info/WHEEL
mambio-0.1.2.dist-info/METADATA
mambio-0.1.2.dist-info/RECORD
